setup.py
pycrontasks/__init__.py
pycrontasks/deco.py
pycrontasks/errors.py
pycrontasks/manager.py
pycrontasks/task.py
pycrontasks.egg-info/PKG-INFO
pycrontasks.egg-info/SOURCES.txt
pycrontasks.egg-info/dependency_links.txt
pycrontasks.egg-info/requires.txt
pycrontasks.egg-info/top_level.txt